iuse/__init__.py
iuse-0.0.1.dist-info/METADATA
iuse-0.0.1.dist-info/WHEEL
iuse-0.0.1.dist-info/top_level.txt
iuse-0.0.1.dist-info/RECORD
