Metadata-Version: 2.1
Name: iuse
Version: 0.0.1
Summary: Collection of utilities for PyTorch and PyTorch-Ignite
Home-page: https://github.com/ydcjeff/iuse
Author: Jeff Yang
Author-email: UNKNOWN
License: MIT
Platform: UNKNOWN
